{
  "canvas": {
    "figure_width": 7.4,
    "figure_height": 3.8,
    "dpi": 220,
    "figure_facecolor": "#FFFFFF",
    "axes_facecolor": "#FFFFFF",
    "output_dir": "figures/prefetcher",
    "output_basename": "learner_sensitivity_bar_chart"
  },
  "text": {
    "font_family": "DejaVu Sans",
    "font_size": 14,
    "axis_label_size": 16,
    "tick_label_size": 14,
    "legend_font_size": 13,
    "y_label_text": "Normalized Perf.",
    "x_tick_rotation": 25,
    "title_text": "",
    "title_size": 18,
    "label_color": "#222222",
    "tick_color": "#222222",
    "title_color": "#102A43"
  },
  "axes": {
    "grid_color": "#D7D7D7",
    "grid_line_width": 1.0,
    "grid_alpha": 1.0,
    "spine_color": "#656667",
    "spine_line_width": 1.0,
    "x_margin": 0.01,
    "baseline_y": 1.0,
    "baseline_color": "#F4C542",
    "baseline_line_width": 2.0,
    "baseline_line_style": "--",
    "y_min": 0.0,
    "y_max": 5.2
  },
  "bars": {
    "bar_width": 0.2,
    "edgecolor": "none",
    "line_width": 0.0
  },
  "legend": {
    "columns": 3,
    "location": "lower left",
    "bbox_to_anchor": [0.0, 1.01, 1.0, 0.24],
    "mode": "expand",
    "columnspacing": 1.6,
    "handlelength": 1.6,
    "handletextpad": 0.6,
    "labelspacing": 0.8,
    "borderaxespad": 0.0,
    "order": ["Baseline", "4 learners", "1 learner", "2 learners", "3 learners"]
  },
  "series": {
    "baseline": {
      "label": "Baseline",
      "color": "#F4C542"
    },
    "bars": {
      "1 learner": "#ADDEEB",
      "2 learners": "#83CEE2",
      "3 learners": "#5ABED8",
      "4 learners": "#ED6612"
    }
  }
}
